lassoreg/__init__.py
lassoreg/regression.py
lassoreg/__pycache__/regression.cpython-311.pyc
lassoreg-0.1.1.dist-info/METADATA
lassoreg-0.1.1.dist-info/WHEEL
lassoreg-0.1.1.dist-info/top_level.txt
lassoreg-0.1.1.dist-info/RECORD
