Metadata-Version: 2.1
Name: lassoreg
Version: 0.1.1
Summary: My wonderful Lasso Regression Python package
Author-email: Ramon Perez <ramon.perez@seldon.io>
License: MIT License
Project-URL: Source, https://github.com/ramonpzg/architecting_tools/tree/main/first_package
Keywords: statistics,lasso,lasso regression,Regression,Model,Statistical Model
Requires-Python: >=3.11
Requires-Dist: numpy
Requires-Dist: importlib-metadata
